README.md
setup.py
api_responses/__init__.py
api_responses/responses.py
api_responses.egg-info/PKG-INFO
api_responses.egg-info/SOURCES.txt
api_responses.egg-info/dependency_links.txt
api_responses.egg-info/top_level.txt