Metadata-Version: 2.1
Name: api-responses
Version: 0.0.1
License: MIT
